containerregistry/__init__.py
containerregistry/client/__init__.py
containerregistry/client/docker_creds_.py
containerregistry/client/docker_name_.py
containerregistry/client/monitor_.py
containerregistry/client/v1/__init__.py
containerregistry/client/v1/docker_creds_.py
containerregistry/client/v1/docker_http_.py
containerregistry/client/v1/docker_image_.py
containerregistry/client/v1/docker_session_.py
containerregistry/client/v1/save_.py
containerregistry/client/v2/__init__.py
containerregistry/client/v2/append_.py
containerregistry/client/v2/docker_creds_.py
containerregistry/client/v2/docker_digest_.py
containerregistry/client/v2/docker_http_.py
containerregistry/client/v2/docker_image_.py
containerregistry/client/v2/docker_session_.py
containerregistry/client/v2/util_.py
containerregistry/client/v2/v1_compat_.py
containerregistry/client/v2_2/__init__.py
containerregistry/client/v2_2/append_.py
containerregistry/client/v2_2/docker_creds_.py
containerregistry/client/v2_2/docker_digest_.py
containerregistry/client/v2_2/docker_http_.py
containerregistry/client/v2_2/docker_image_.py
containerregistry/client/v2_2/docker_image_list_.py
containerregistry/client/v2_2/docker_session_.py
containerregistry/client/v2_2/oci_compat_.py
containerregistry/client/v2_2/save_.py
containerregistry/client/v2_2/v2_compat_.py
containerregistry/transform/__init__.py
containerregistry/transform/v2_2/__init__.py
containerregistry/transform/v2_2/metadata_.py
containerregistry/transport/__init__.py
containerregistry/transport/nested_.py
containerregistry/transport/retry_.py
containerregistry/transport/transport_pool_.py
fairing/__init__.py
fairing/config.py
fairing/http_utils.py
fairing/runtime_config.py
fairing/utils.py
fairing/backends/__init__.py
fairing/backends/backends.py
fairing/builders/__init__.py
fairing/builders/base_builder.py
fairing/builders/builder.py
fairing/builders/dockerfile.py
fairing/builders/append/__init__.py
fairing/builders/append/append.py
fairing-0.5.3.dist-info/LICENSE
fairing-0.5.3.dist-info/METADATA
fairing-0.5.3.dist-info/WHEEL
fairing-0.5.3.dist-info/top_level.txt
fairing-0.5.3.dist-info/RECORD
